{
   "NAME": "entity_sequence_clusters", 
   "SLICE_PARENT_ITEMS": {}, 
   "SCHEMA_DICT": {
      "SOFTWARE": {
         "SLICE_CATEGORY_EXTRAS": {}, 
         "MAP_MERGE_INDICES": {
            "software": {
               "TYPE": "EQUI-JOIN", 
               "ATTRIBUTES": [
                  "pdbx_ordinal"
               ]
            }
         }, 
         "ATTRIBUTE_MAP": {
            "DESCRIPTION": {
               "METHOD_NAME": null, 
               "CATEGORY": "software", 
               "ATTRIBUTE": "description", 
               "ARGUMENTS": null
            }, 
            "COMPILER_VERSION": {
               "METHOD_NAME": null, 
               "CATEGORY": "software", 
               "ATTRIBUTE": "compiler_version", 
               "ARGUMENTS": null
            }, 
            "COMPILER_NAME": {
               "METHOD_NAME": null, 
               "CATEGORY": "software", 
               "ATTRIBUTE": "compiler_name", 
               "ARGUMENTS": null
            }, 
            "CONTACT_AUTHOR_EMAIL": {
               "METHOD_NAME": null, 
               "CATEGORY": "software", 
               "ATTRIBUTE": "contact_author_email", 
               "ARGUMENTS": null
            }, 
            "PDBX_ORDINAL": {
               "METHOD_NAME": null, 
               "CATEGORY": "software", 
               "ATTRIBUTE": "pdbx_ordinal", 
               "ARGUMENTS": null
            }, 
            "TYPE": {
               "METHOD_NAME": null, 
               "CATEGORY": "software", 
               "ATTRIBUTE": "type", 
               "ARGUMENTS": null
            }, 
            "CITATION_ID": {
               "METHOD_NAME": null, 
               "CATEGORY": "software", 
               "ATTRIBUTE": "citation_id", 
               "ARGUMENTS": null
            }, 
            "MODS": {
               "METHOD_NAME": null, 
               "CATEGORY": "software", 
               "ATTRIBUTE": "mods", 
               "ARGUMENTS": null
            }, 
            "CONTACT_AUTHOR": {
               "METHOD_NAME": null, 
               "CATEGORY": "software", 
               "ATTRIBUTE": "contact_author", 
               "ARGUMENTS": null
            }, 
            "CLASSIFICATION": {
               "METHOD_NAME": null, 
               "CATEGORY": "software", 
               "ATTRIBUTE": "classification", 
               "ARGUMENTS": null
            }, 
            "LANGUAGE": {
               "METHOD_NAME": null, 
               "CATEGORY": "software", 
               "ATTRIBUTE": "language", 
               "ARGUMENTS": null
            }, 
            "LOCATION": {
               "METHOD_NAME": null, 
               "CATEGORY": "software", 
               "ATTRIBUTE": "location", 
               "ARGUMENTS": null
            }, 
            "HARDWARE": {
               "METHOD_NAME": null, 
               "CATEGORY": "software", 
               "ATTRIBUTE": "hardware", 
               "ARGUMENTS": null
            }, 
            "OS_VERSION": {
               "METHOD_NAME": null, 
               "CATEGORY": "software", 
               "ATTRIBUTE": "os_version", 
               "ARGUMENTS": null
            }, 
            "DEPENDENCIES": {
               "METHOD_NAME": null, 
               "CATEGORY": "software", 
               "ATTRIBUTE": "dependencies", 
               "ARGUMENTS": null
            }, 
            "OS": {
               "METHOD_NAME": null, 
               "CATEGORY": "software", 
               "ATTRIBUTE": "os", 
               "ARGUMENTS": null
            }, 
            "VERSION": {
               "METHOD_NAME": null, 
               "CATEGORY": "software", 
               "ATTRIBUTE": "version", 
               "ARGUMENTS": null
            }, 
            "DATE": {
               "METHOD_NAME": null, 
               "CATEGORY": "software", 
               "ATTRIBUTE": "date", 
               "ARGUMENTS": null
            }, 
            "NAME": {
               "METHOD_NAME": null, 
               "CATEGORY": "software", 
               "ATTRIBUTE": "name", 
               "ARGUMENTS": null
            }
         }, 
         "SCHEMA_DELETE_ATTRIBUTE": null, 
         "SLICE_UNIT_CARDINALITY": {}, 
         "SCHEMA_NAME": "software", 
         "SCHEMA_TYPE": "transactional", 
         "SCHEMA_CONTENT_CLASSES": [], 
         "SCHEMA_MANDATORY": false, 
         "SCHEMA_ID": "SOFTWARE", 
         "SCHEMA_UNIT_CARDINALITY": false, 
         "SLICE_ATTRIBUTES": {}, 
         "INDICES": {
            "p1": {
               "TYPE": "UNIQUE", 
               "ATTRIBUTES": [
                  "PDBX_ORDINAL"
               ]
            }
         }, 
         "ATTRIBUTES": {
            "COMPILER_VERSION": "compiler_version", 
            "CONTACT_AUTHOR_EMAIL": "contact_author_email", 
            "VERSION": "version", 
            "CONTACT_AUTHOR": "contact_author", 
            "CLASSIFICATION": "classification", 
            "OS": "os", 
            "HARDWARE": "hardware", 
            "OS_VERSION": "os_version", 
            "DEPENDENCIES": "dependencies", 
            "DATE": "date", 
            "DESCRIPTION": "description", 
            "LANGUAGE": "language", 
            "COMPILER_NAME": "compiler_name", 
            "MODS": "mods", 
            "PDBX_ORDINAL": "pdbx_ordinal", 
            "CITATION_ID": "citation_id", 
            "LOCATION": "location", 
            "TYPE": "type", 
            "NAME": "name"
         }, 
         "ATTRIBUTE_INFO": {
            "DESCRIPTION": {
               "APP_TYPE": "char", 
               "ENUMERATION": {}, 
               "FILTER_TYPES": [], 
               "WIDTH": 10, 
               "ORDER": 10, 
               "PRIMARY_KEY": false, 
               "NULLABLE": true, 
               "PRECISION": 0, 
               "IS_CHAR_TYPE": true, 
               "ITERABLE_DELIMITER": null, 
               "CONTENT_CLASSES": []
            }, 
            "COMPILER_VERSION": {
               "APP_TYPE": "char", 
               "ENUMERATION": {}, 
               "FILTER_TYPES": [], 
               "WIDTH": 10, 
               "ORDER": 5, 
               "PRIMARY_KEY": false, 
               "NULLABLE": true, 
               "PRECISION": 0, 
               "IS_CHAR_TYPE": true, 
               "ITERABLE_DELIMITER": null, 
               "CONTENT_CLASSES": []
            }, 
            "COMPILER_NAME": {
               "APP_TYPE": "char", 
               "ENUMERATION": {}, 
               "FILTER_TYPES": [], 
               "WIDTH": 10, 
               "ORDER": 4, 
               "PRIMARY_KEY": false, 
               "NULLABLE": true, 
               "PRECISION": 0, 
               "IS_CHAR_TYPE": true, 
               "ITERABLE_DELIMITER": null, 
               "CONTENT_CLASSES": []
            }, 
            "CONTACT_AUTHOR_EMAIL": {
               "APP_TYPE": "char", 
               "ENUMERATION": {}, 
               "FILTER_TYPES": [], 
               "WIDTH": 10, 
               "ORDER": 7, 
               "PRIMARY_KEY": false, 
               "NULLABLE": true, 
               "PRECISION": 0, 
               "IS_CHAR_TYPE": true, 
               "ITERABLE_DELIMITER": null, 
               "CONTENT_CLASSES": []
            }, 
            "PDBX_ORDINAL": {
               "APP_TYPE": "int", 
               "ENUMERATION": {}, 
               "FILTER_TYPES": [], 
               "WIDTH": 10, 
               "ORDER": 1, 
               "PRIMARY_KEY": true, 
               "NULLABLE": false, 
               "PRECISION": 0, 
               "IS_CHAR_TYPE": false, 
               "ITERABLE_DELIMITER": null, 
               "CONTENT_CLASSES": []
            }, 
            "TYPE": {
               "APP_TYPE": "char", 
               "ENUMERATION": {
                  "package": "package", 
                  "library": "library", 
                  "program": "program", 
                  "filter": "filter", 
                  "jiffy": "jiffy", 
                  "other": "other"
               }, 
               "FILTER_TYPES": [], 
               "WIDTH": 10, 
               "ORDER": 18, 
               "PRIMARY_KEY": false, 
               "NULLABLE": true, 
               "PRECISION": 0, 
               "IS_CHAR_TYPE": true, 
               "ITERABLE_DELIMITER": null, 
               "CONTENT_CLASSES": []
            }, 
            "CITATION_ID": {
               "APP_TYPE": "char", 
               "ENUMERATION": {}, 
               "FILTER_TYPES": [], 
               "WIDTH": 10, 
               "ORDER": 2, 
               "PRIMARY_KEY": false, 
               "NULLABLE": true, 
               "PRECISION": 0, 
               "IS_CHAR_TYPE": true, 
               "ITERABLE_DELIMITER": null, 
               "CONTENT_CLASSES": []
            }, 
            "MODS": {
               "APP_TYPE": "char", 
               "ENUMERATION": {}, 
               "FILTER_TYPES": [], 
               "WIDTH": 10, 
               "ORDER": 14, 
               "PRIMARY_KEY": false, 
               "NULLABLE": true, 
               "PRECISION": 0, 
               "IS_CHAR_TYPE": true, 
               "ITERABLE_DELIMITER": null, 
               "CONTENT_CLASSES": []
            }, 
            "CONTACT_AUTHOR": {
               "APP_TYPE": "char", 
               "ENUMERATION": {}, 
               "FILTER_TYPES": [], 
               "WIDTH": 10, 
               "ORDER": 6, 
               "PRIMARY_KEY": false, 
               "NULLABLE": true, 
               "PRECISION": 0, 
               "IS_CHAR_TYPE": true, 
               "ITERABLE_DELIMITER": null, 
               "CONTENT_CLASSES": []
            }, 
            "CLASSIFICATION": {
               "APP_TYPE": "char", 
               "ENUMERATION": {}, 
               "FILTER_TYPES": [], 
               "WIDTH": 10, 
               "ORDER": 3, 
               "PRIMARY_KEY": false, 
               "NULLABLE": false, 
               "PRECISION": 0, 
               "IS_CHAR_TYPE": true, 
               "ITERABLE_DELIMITER": null, 
               "CONTENT_CLASSES": []
            }, 
            "LANGUAGE": {
               "APP_TYPE": "char", 
               "ENUMERATION": {
                  "pascal": "Pascal", 
                  "assembler": "assembler", 
                  "tcl": "Tcl", 
                  "java & fortran": "Java & Fortran", 
                  "java": "Java", 
                  "csh": "csh", 
                  "python/c++": "Python/C++", 
                  "perl": "Perl", 
                  "ada": "Ada", 
                  "fortran": "Fortran", 
                  "other": "Other", 
                  "ksh": "ksh", 
                  "c/c++": "C/C++", 
                  "fortran 90": "Fortran 90", 
                  "python": "Python", 
                  "awk": "Awk", 
                  "fortran_77": "Fortran_77", 
                  "basic": "Basic", 
                  "c": "C", 
                  "fortran 77": "Fortran 77", 
                  "sh": "sh", 
                  "c++": "C++"
               }, 
               "FILTER_TYPES": [], 
               "WIDTH": 10, 
               "ORDER": 12, 
               "PRIMARY_KEY": false, 
               "NULLABLE": true, 
               "PRECISION": 0, 
               "IS_CHAR_TYPE": true, 
               "ITERABLE_DELIMITER": null, 
               "CONTENT_CLASSES": []
            }, 
            "LOCATION": {
               "APP_TYPE": "char", 
               "ENUMERATION": {}, 
               "FILTER_TYPES": [], 
               "WIDTH": 10, 
               "ORDER": 13, 
               "PRIMARY_KEY": false, 
               "NULLABLE": true, 
               "PRECISION": 0, 
               "IS_CHAR_TYPE": true, 
               "ITERABLE_DELIMITER": null, 
               "CONTENT_CLASSES": []
            }, 
            "HARDWARE": {
               "APP_TYPE": "char", 
               "ENUMERATION": {}, 
               "FILTER_TYPES": [], 
               "WIDTH": 10, 
               "ORDER": 11, 
               "PRIMARY_KEY": false, 
               "NULLABLE": true, 
               "PRECISION": 0, 
               "IS_CHAR_TYPE": true, 
               "ITERABLE_DELIMITER": null, 
               "CONTENT_CLASSES": []
            }, 
            "OS_VERSION": {
               "APP_TYPE": "char", 
               "ENUMERATION": {}, 
               "FILTER_TYPES": [], 
               "WIDTH": 10, 
               "ORDER": 17, 
               "PRIMARY_KEY": false, 
               "NULLABLE": true, 
               "PRECISION": 0, 
               "IS_CHAR_TYPE": true, 
               "ITERABLE_DELIMITER": null, 
               "CONTENT_CLASSES": []
            }, 
            "DEPENDENCIES": {
               "APP_TYPE": "char", 
               "ENUMERATION": {}, 
               "FILTER_TYPES": [], 
               "WIDTH": 10, 
               "ORDER": 9, 
               "PRIMARY_KEY": false, 
               "NULLABLE": true, 
               "PRECISION": 0, 
               "IS_CHAR_TYPE": true, 
               "ITERABLE_DELIMITER": null, 
               "CONTENT_CLASSES": []
            }, 
            "OS": {
               "APP_TYPE": "char", 
               "ENUMERATION": {}, 
               "FILTER_TYPES": [], 
               "WIDTH": 10, 
               "ORDER": 16, 
               "PRIMARY_KEY": false, 
               "NULLABLE": true, 
               "PRECISION": 0, 
               "IS_CHAR_TYPE": true, 
               "ITERABLE_DELIMITER": null, 
               "CONTENT_CLASSES": []
            }, 
            "VERSION": {
               "APP_TYPE": "char", 
               "ENUMERATION": {}, 
               "FILTER_TYPES": [], 
               "WIDTH": 10, 
               "ORDER": 19, 
               "PRIMARY_KEY": false, 
               "NULLABLE": true, 
               "PRECISION": 0, 
               "IS_CHAR_TYPE": true, 
               "ITERABLE_DELIMITER": null, 
               "CONTENT_CLASSES": []
            }, 
            "DATE": {
               "APP_TYPE": "char", 
               "ENUMERATION": {}, 
               "FILTER_TYPES": [], 
               "WIDTH": 10, 
               "ORDER": 8, 
               "PRIMARY_KEY": false, 
               "NULLABLE": true, 
               "PRECISION": 0, 
               "IS_CHAR_TYPE": true, 
               "ITERABLE_DELIMITER": null, 
               "CONTENT_CLASSES": []
            }, 
            "NAME": {
               "APP_TYPE": "char", 
               "ENUMERATION": {}, 
               "FILTER_TYPES": [], 
               "WIDTH": 10, 
               "ORDER": 15, 
               "PRIMARY_KEY": false, 
               "NULLABLE": false, 
               "PRECISION": 0, 
               "IS_CHAR_TYPE": true, 
               "ITERABLE_DELIMITER": null, 
               "CONTENT_CLASSES": []
            }
         }
      }, 
      "CITATION_AUTHOR": {
         "SLICE_CATEGORY_EXTRAS": {}, 
         "MAP_MERGE_INDICES": {
            "citation_author": {
               "TYPE": "EQUI-JOIN", 
               "ATTRIBUTES": [
                  "citation_id", 
                  "name", 
                  "ordinal"
               ]
            }
         }, 
         "ATTRIBUTE_MAP": {
            "NAME": {
               "METHOD_NAME": null, 
               "CATEGORY": "citation_author", 
               "ATTRIBUTE": "name", 
               "ARGUMENTS": null
            }, 
            "CITATION_ID": {
               "METHOD_NAME": null, 
               "CATEGORY": "citation_author", 
               "ATTRIBUTE": "citation_id", 
               "ARGUMENTS": null
            }, 
            "ORDINAL": {
               "METHOD_NAME": null, 
               "CATEGORY": "citation_author", 
               "ATTRIBUTE": "ordinal", 
               "ARGUMENTS": null
            }, 
            "IDENTIFIER_ORCID": {
               "METHOD_NAME": null, 
               "CATEGORY": "citation_author", 
               "ATTRIBUTE": "identifier_ORCID", 
               "ARGUMENTS": null
            }
         }, 
         "SCHEMA_DELETE_ATTRIBUTE": null, 
         "SLICE_UNIT_CARDINALITY": {}, 
         "SCHEMA_NAME": "citation_author", 
         "SCHEMA_TYPE": "transactional", 
         "SCHEMA_CONTENT_CLASSES": [], 
         "SCHEMA_MANDATORY": false, 
         "SCHEMA_ID": "CITATION_AUTHOR", 
         "SCHEMA_UNIT_CARDINALITY": false, 
         "SLICE_ATTRIBUTES": {}, 
         "INDICES": {
            "s1": {
               "TYPE": "SEARCH", 
               "ATTRIBUTES": [
                  null
               ]
            }, 
            "p1": {
               "TYPE": "UNIQUE", 
               "ATTRIBUTES": [
                  "CITATION_ID", 
                  "NAME", 
                  "ORDINAL"
               ]
            }
         }, 
         "ATTRIBUTES": {
            "NAME": "name", 
            "CITATION_ID": "citation_id", 
            "ORDINAL": "ordinal", 
            "IDENTIFIER_ORCID": "identifier_ORCID"
         }, 
         "ATTRIBUTE_INFO": {
            "NAME": {
               "APP_TYPE": "char", 
               "ENUMERATION": {}, 
               "FILTER_TYPES": [], 
               "WIDTH": 10, 
               "ORDER": 2, 
               "PRIMARY_KEY": true, 
               "NULLABLE": false, 
               "PRECISION": 0, 
               "IS_CHAR_TYPE": true, 
               "ITERABLE_DELIMITER": null, 
               "CONTENT_CLASSES": []
            }, 
            "CITATION_ID": {
               "APP_TYPE": "char", 
               "ENUMERATION": {}, 
               "FILTER_TYPES": [], 
               "WIDTH": 10, 
               "ORDER": 1, 
               "PRIMARY_KEY": true, 
               "NULLABLE": false, 
               "PRECISION": 0, 
               "IS_CHAR_TYPE": true, 
               "ITERABLE_DELIMITER": null, 
               "CONTENT_CLASSES": []
            }, 
            "ORDINAL": {
               "APP_TYPE": "int", 
               "ENUMERATION": {}, 
               "FILTER_TYPES": [], 
               "WIDTH": 10, 
               "ORDER": 3, 
               "PRIMARY_KEY": true, 
               "NULLABLE": false, 
               "PRECISION": 0, 
               "IS_CHAR_TYPE": false, 
               "ITERABLE_DELIMITER": null, 
               "CONTENT_CLASSES": []
            }, 
            "IDENTIFIER_ORCID": {
               "APP_TYPE": "char", 
               "ENUMERATION": {}, 
               "FILTER_TYPES": [], 
               "WIDTH": 10, 
               "ORDER": 4, 
               "PRIMARY_KEY": false, 
               "NULLABLE": true, 
               "PRECISION": 0, 
               "IS_CHAR_TYPE": true, 
               "ITERABLE_DELIMITER": null, 
               "CONTENT_CLASSES": []
            }
         }
      }, 
      "RCSB_INSTANCE_SEQUENCE_CLUSTER_LIST": {
         "SLICE_CATEGORY_EXTRAS": {}, 
         "MAP_MERGE_INDICES": {
            "rcsb_instance_sequence_cluster_list": {
               "TYPE": "EQUI-JOIN", 
               "ATTRIBUTES": [
                  "cluster_id", 
                  "data_set_id", 
                  "entry_id", 
                  "identity"
               ]
            }
         }, 
         "ATTRIBUTE_MAP": {
            "CLUSTER_ID": {
               "METHOD_NAME": null, 
               "CATEGORY": "rcsb_instance_sequence_cluster_list", 
               "ATTRIBUTE": "cluster_id", 
               "ARGUMENTS": null
            }, 
            "ENTRY_ID": {
               "METHOD_NAME": null, 
               "CATEGORY": "rcsb_instance_sequence_cluster_list", 
               "ATTRIBUTE": "entry_id", 
               "ARGUMENTS": null
            }, 
            "IDENTITY": {
               "METHOD_NAME": null, 
               "CATEGORY": "rcsb_instance_sequence_cluster_list", 
               "ATTRIBUTE": "identity", 
               "ARGUMENTS": null
            }, 
            "INSTANCE_ID": {
               "METHOD_NAME": null, 
               "CATEGORY": "rcsb_instance_sequence_cluster_list", 
               "ATTRIBUTE": "instance_id", 
               "ARGUMENTS": null
            }, 
            "DATA_SET_ID": {
               "METHOD_NAME": null, 
               "CATEGORY": "rcsb_instance_sequence_cluster_list", 
               "ATTRIBUTE": "data_set_id", 
               "ARGUMENTS": null
            }
         }, 
         "SCHEMA_DELETE_ATTRIBUTE": null, 
         "SLICE_UNIT_CARDINALITY": {}, 
         "SCHEMA_NAME": "rcsb_instance_sequence_cluster_list", 
         "SCHEMA_TYPE": "transactional", 
         "SCHEMA_CONTENT_CLASSES": [
            "SEQUENCE_CLUSTER_CONTENT"
         ], 
         "SCHEMA_MANDATORY": false, 
         "SCHEMA_ID": "RCSB_INSTANCE_SEQUENCE_CLUSTER_LIST", 
         "SCHEMA_UNIT_CARDINALITY": false, 
         "SLICE_ATTRIBUTES": {}, 
         "INDICES": {
            "s1": {
               "TYPE": "SEARCH", 
               "ATTRIBUTES": [
                  null
               ]
            }, 
            "p1": {
               "TYPE": "UNIQUE", 
               "ATTRIBUTES": [
                  "CLUSTER_ID", 
                  "DATA_SET_ID", 
                  "ENTRY_ID", 
                  "IDENTITY"
               ]
            }
         }, 
         "ATTRIBUTES": {
            "CLUSTER_ID": "cluster_id", 
            "ENTRY_ID": "entry_id", 
            "IDENTITY": "identity", 
            "DATA_SET_ID": "data_set_id", 
            "INSTANCE_ID": "instance_id"
         }, 
         "ATTRIBUTE_INFO": {
            "CLUSTER_ID": {
               "APP_TYPE": "int", 
               "ENUMERATION": {}, 
               "FILTER_TYPES": [], 
               "WIDTH": 10, 
               "ORDER": 1, 
               "PRIMARY_KEY": true, 
               "NULLABLE": false, 
               "PRECISION": 0, 
               "IS_CHAR_TYPE": false, 
               "ITERABLE_DELIMITER": null, 
               "CONTENT_CLASSES": [
                  "SEQUENCE_CLUSTER_CONTENT"
               ]
            }, 
            "ENTRY_ID": {
               "APP_TYPE": "char", 
               "ENUMERATION": {}, 
               "FILTER_TYPES": [], 
               "WIDTH": 10, 
               "ORDER": 3, 
               "PRIMARY_KEY": true, 
               "NULLABLE": false, 
               "PRECISION": 0, 
               "IS_CHAR_TYPE": true, 
               "ITERABLE_DELIMITER": null, 
               "CONTENT_CLASSES": [
                  "SEQUENCE_CLUSTER_CONTENT"
               ]
            }, 
            "IDENTITY": {
               "APP_TYPE": "int", 
               "ENUMERATION": {}, 
               "FILTER_TYPES": [], 
               "WIDTH": 10, 
               "ORDER": 4, 
               "PRIMARY_KEY": true, 
               "NULLABLE": false, 
               "PRECISION": 0, 
               "IS_CHAR_TYPE": false, 
               "ITERABLE_DELIMITER": null, 
               "CONTENT_CLASSES": [
                  "SEQUENCE_CLUSTER_CONTENT"
               ]
            }, 
            "INSTANCE_ID": {
               "APP_TYPE": "char", 
               "ENUMERATION": {}, 
               "FILTER_TYPES": [], 
               "WIDTH": 10, 
               "ORDER": 5, 
               "PRIMARY_KEY": false, 
               "NULLABLE": false, 
               "PRECISION": 0, 
               "IS_CHAR_TYPE": true, 
               "ITERABLE_DELIMITER": null, 
               "CONTENT_CLASSES": [
                  "SEQUENCE_CLUSTER_CONTENT"
               ]
            }, 
            "DATA_SET_ID": {
               "APP_TYPE": "char", 
               "ENUMERATION": {}, 
               "FILTER_TYPES": [], 
               "WIDTH": 10, 
               "ORDER": 2, 
               "PRIMARY_KEY": true, 
               "NULLABLE": false, 
               "PRECISION": 0, 
               "IS_CHAR_TYPE": true, 
               "ITERABLE_DELIMITER": null, 
               "CONTENT_CLASSES": [
                  "SEQUENCE_CLUSTER_CONTENT"
               ]
            }
         }
      }, 
      "RCSB_ENTITY_SEQUENCE_CLUSTER_LIST": {
         "SLICE_CATEGORY_EXTRAS": {}, 
         "MAP_MERGE_INDICES": {
            "rcsb_entity_sequence_cluster_list": {
               "TYPE": "EQUI-JOIN", 
               "ATTRIBUTES": [
                  "cluster_id", 
                  "data_set_id", 
                  "entity_id", 
                  "entry_id", 
                  "identity"
               ]
            }
         }, 
         "ATTRIBUTE_MAP": {
            "CLUSTER_ID": {
               "METHOD_NAME": null, 
               "CATEGORY": "rcsb_entity_sequence_cluster_list", 
               "ATTRIBUTE": "cluster_id", 
               "ARGUMENTS": null
            }, 
            "ENTRY_ID": {
               "METHOD_NAME": null, 
               "CATEGORY": "rcsb_entity_sequence_cluster_list", 
               "ATTRIBUTE": "entry_id", 
               "ARGUMENTS": null
            }, 
            "IDENTITY": {
               "METHOD_NAME": null, 
               "CATEGORY": "rcsb_entity_sequence_cluster_list", 
               "ATTRIBUTE": "identity", 
               "ARGUMENTS": null
            }, 
            "DATA_SET_ID": {
               "METHOD_NAME": null, 
               "CATEGORY": "rcsb_entity_sequence_cluster_list", 
               "ATTRIBUTE": "data_set_id", 
               "ARGUMENTS": null
            }, 
            "ENTITY_ID": {
               "METHOD_NAME": null, 
               "CATEGORY": "rcsb_entity_sequence_cluster_list", 
               "ATTRIBUTE": "entity_id", 
               "ARGUMENTS": null
            }
         }, 
         "SCHEMA_DELETE_ATTRIBUTE": null, 
         "SLICE_UNIT_CARDINALITY": {}, 
         "SCHEMA_NAME": "rcsb_entity_sequence_cluster_list", 
         "SCHEMA_TYPE": "transactional", 
         "SCHEMA_CONTENT_CLASSES": [
            "SEQUENCE_CLUSTER_CONTENT"
         ], 
         "SCHEMA_MANDATORY": false, 
         "SCHEMA_ID": "RCSB_ENTITY_SEQUENCE_CLUSTER_LIST", 
         "SCHEMA_UNIT_CARDINALITY": false, 
         "SLICE_ATTRIBUTES": {}, 
         "INDICES": {
            "s1": {
               "TYPE": "SEARCH", 
               "ATTRIBUTES": [
                  null
               ]
            }, 
            "p1": {
               "TYPE": "UNIQUE", 
               "ATTRIBUTES": [
                  "CLUSTER_ID", 
                  "DATA_SET_ID", 
                  "ENTITY_ID", 
                  "ENTRY_ID", 
                  "IDENTITY"
               ]
            }
         }, 
         "ATTRIBUTES": {
            "CLUSTER_ID": "cluster_id", 
            "ENTRY_ID": "entry_id", 
            "IDENTITY": "identity", 
            "DATA_SET_ID": "data_set_id", 
            "ENTITY_ID": "entity_id"
         }, 
         "ATTRIBUTE_INFO": {
            "CLUSTER_ID": {
               "APP_TYPE": "int", 
               "ENUMERATION": {}, 
               "FILTER_TYPES": [], 
               "WIDTH": 10, 
               "ORDER": 1, 
               "PRIMARY_KEY": true, 
               "NULLABLE": false, 
               "PRECISION": 0, 
               "IS_CHAR_TYPE": false, 
               "ITERABLE_DELIMITER": null, 
               "CONTENT_CLASSES": [
                  "SEQUENCE_CLUSTER_CONTENT"
               ]
            }, 
            "ENTRY_ID": {
               "APP_TYPE": "char", 
               "ENUMERATION": {}, 
               "FILTER_TYPES": [], 
               "WIDTH": 10, 
               "ORDER": 4, 
               "PRIMARY_KEY": true, 
               "NULLABLE": false, 
               "PRECISION": 0, 
               "IS_CHAR_TYPE": true, 
               "ITERABLE_DELIMITER": null, 
               "CONTENT_CLASSES": [
                  "SEQUENCE_CLUSTER_CONTENT"
               ]
            }, 
            "IDENTITY": {
               "APP_TYPE": "int", 
               "ENUMERATION": {}, 
               "FILTER_TYPES": [], 
               "WIDTH": 10, 
               "ORDER": 5, 
               "PRIMARY_KEY": true, 
               "NULLABLE": false, 
               "PRECISION": 0, 
               "IS_CHAR_TYPE": false, 
               "ITERABLE_DELIMITER": null, 
               "CONTENT_CLASSES": [
                  "SEQUENCE_CLUSTER_CONTENT"
               ]
            }, 
            "DATA_SET_ID": {
               "APP_TYPE": "char", 
               "ENUMERATION": {}, 
               "FILTER_TYPES": [], 
               "WIDTH": 10, 
               "ORDER": 2, 
               "PRIMARY_KEY": true, 
               "NULLABLE": false, 
               "PRECISION": 0, 
               "IS_CHAR_TYPE": true, 
               "ITERABLE_DELIMITER": null, 
               "CONTENT_CLASSES": [
                  "SEQUENCE_CLUSTER_CONTENT"
               ]
            }, 
            "ENTITY_ID": {
               "APP_TYPE": "char", 
               "ENUMERATION": {}, 
               "FILTER_TYPES": [], 
               "WIDTH": 10, 
               "ORDER": 3, 
               "PRIMARY_KEY": true, 
               "NULLABLE": false, 
               "PRECISION": 0, 
               "IS_CHAR_TYPE": true, 
               "ITERABLE_DELIMITER": null, 
               "CONTENT_CLASSES": [
                  "SEQUENCE_CLUSTER_CONTENT"
               ]
            }
         }
      }, 
      "CITATION": {
         "SLICE_CATEGORY_EXTRAS": {}, 
         "MAP_MERGE_INDICES": {
            "citation": {
               "TYPE": "EQUI-JOIN", 
               "ATTRIBUTES": [
                  "id"
               ]
            }
         }, 
         "ATTRIBUTE_MAP": {
            "JOURNAL_ID_CSD": {
               "METHOD_NAME": null, 
               "CATEGORY": "citation", 
               "ATTRIBUTE": "journal_id_CSD", 
               "ARGUMENTS": null
            }, 
            "BOOK_PUBLISHER_CITY": {
               "METHOD_NAME": null, 
               "CATEGORY": "citation", 
               "ATTRIBUTE": "book_publisher_city", 
               "ARGUMENTS": null
            }, 
            "COORDINATE_LINKAGE": {
               "METHOD_NAME": null, 
               "CATEGORY": "citation", 
               "ATTRIBUTE": "coordinate_linkage", 
               "ARGUMENTS": null
            }, 
            "JOURNAL_ABBREV": {
               "METHOD_NAME": null, 
               "CATEGORY": "citation", 
               "ATTRIBUTE": "journal_abbrev", 
               "ARGUMENTS": null
            }, 
            "PAGE_FIRST": {
               "METHOD_NAME": null, 
               "CATEGORY": "citation", 
               "ATTRIBUTE": "page_first", 
               "ARGUMENTS": null
            }, 
            "TITLE": {
               "METHOD_NAME": null, 
               "CATEGORY": "citation", 
               "ATTRIBUTE": "title", 
               "ARGUMENTS": null
            }, 
            "DATABASE_ID_MEDLINE": {
               "METHOD_NAME": null, 
               "CATEGORY": "citation", 
               "ATTRIBUTE": "database_id_Medline", 
               "ARGUMENTS": null
            }, 
            "COUNTRY": {
               "METHOD_NAME": null, 
               "CATEGORY": "citation", 
               "ATTRIBUTE": "country", 
               "ARGUMENTS": null
            }, 
            "ABSTRACT": {
               "METHOD_NAME": null, 
               "CATEGORY": "citation", 
               "ATTRIBUTE": "abstract", 
               "ARGUMENTS": null
            }, 
            "PDBX_DATABASE_ID_PUBMED": {
               "METHOD_NAME": null, 
               "CATEGORY": "citation", 
               "ATTRIBUTE": "pdbx_database_id_PubMed", 
               "ARGUMENTS": null
            }, 
            "DETAILS": {
               "METHOD_NAME": null, 
               "CATEGORY": "citation", 
               "ATTRIBUTE": "details", 
               "ARGUMENTS": null
            }, 
            "ABSTRACT_ID_CAS": {
               "METHOD_NAME": null, 
               "CATEGORY": "citation", 
               "ATTRIBUTE": "abstract_id_CAS", 
               "ARGUMENTS": null
            }, 
            "JOURNAL_FULL": {
               "METHOD_NAME": null, 
               "CATEGORY": "citation", 
               "ATTRIBUTE": "journal_full", 
               "ARGUMENTS": null
            }, 
            "BOOK_TITLE": {
               "METHOD_NAME": null, 
               "CATEGORY": "citation", 
               "ATTRIBUTE": "book_title", 
               "ARGUMENTS": null
            }, 
            "ID": {
               "METHOD_NAME": null, 
               "CATEGORY": "citation", 
               "ATTRIBUTE": "id", 
               "ARGUMENTS": null
            }, 
            "BOOK_PUBLISHER": {
               "METHOD_NAME": null, 
               "CATEGORY": "citation", 
               "ATTRIBUTE": "book_publisher", 
               "ARGUMENTS": null
            }, 
            "LANGUAGE": {
               "METHOD_NAME": null, 
               "CATEGORY": "citation", 
               "ATTRIBUTE": "language", 
               "ARGUMENTS": null
            }, 
            "DATABASE_ID_CSD": {
               "METHOD_NAME": null, 
               "CATEGORY": "citation", 
               "ATTRIBUTE": "database_id_CSD", 
               "ARGUMENTS": null
            }, 
            "PDBX_DATABASE_ID_DOI": {
               "METHOD_NAME": null, 
               "CATEGORY": "citation", 
               "ATTRIBUTE": "pdbx_database_id_DOI", 
               "ARGUMENTS": null
            }, 
            "BOOK_ID_ISBN": {
               "METHOD_NAME": null, 
               "CATEGORY": "citation", 
               "ATTRIBUTE": "book_id_ISBN", 
               "ARGUMENTS": null
            }, 
            "PAGE_LAST": {
               "METHOD_NAME": null, 
               "CATEGORY": "citation", 
               "ATTRIBUTE": "page_last", 
               "ARGUMENTS": null
            }, 
            "RCSB_AUTHORS": {
               "METHOD_NAME": null, 
               "CATEGORY": "citation", 
               "ATTRIBUTE": "rcsb_authors", 
               "ARGUMENTS": null
            }, 
            "JOURNAL_VOLUME": {
               "METHOD_NAME": null, 
               "CATEGORY": "citation", 
               "ATTRIBUTE": "journal_volume", 
               "ARGUMENTS": null
            }, 
            "YEAR": {
               "METHOD_NAME": null, 
               "CATEGORY": "citation", 
               "ATTRIBUTE": "year", 
               "ARGUMENTS": null
            }, 
            "JOURNAL_ID_ISSN": {
               "METHOD_NAME": null, 
               "CATEGORY": "citation", 
               "ATTRIBUTE": "journal_id_ISSN", 
               "ARGUMENTS": null
            }, 
            "JOURNAL_ISSUE": {
               "METHOD_NAME": null, 
               "CATEGORY": "citation", 
               "ATTRIBUTE": "journal_issue", 
               "ARGUMENTS": null
            }, 
            "JOURNAL_ID_ASTM": {
               "METHOD_NAME": null, 
               "CATEGORY": "citation", 
               "ATTRIBUTE": "journal_id_ASTM", 
               "ARGUMENTS": null
            }, 
            "UNPUBLISHED_FLAG": {
               "METHOD_NAME": null, 
               "CATEGORY": "citation", 
               "ATTRIBUTE": "unpublished_flag", 
               "ARGUMENTS": null
            }
         }, 
         "SCHEMA_DELETE_ATTRIBUTE": null, 
         "SLICE_UNIT_CARDINALITY": {}, 
         "SCHEMA_NAME": "citation", 
         "SCHEMA_TYPE": "transactional", 
         "SCHEMA_CONTENT_CLASSES": [], 
         "SCHEMA_MANDATORY": false, 
         "SCHEMA_ID": "CITATION", 
         "SCHEMA_UNIT_CARDINALITY": false, 
         "SLICE_ATTRIBUTES": {}, 
         "INDICES": {
            "p1": {
               "TYPE": "UNIQUE", 
               "ATTRIBUTES": [
                  "ID"
               ]
            }
         }, 
         "ATTRIBUTES": {
            "JOURNAL_ID_CSD": "journal_id_CSD", 
            "BOOK_PUBLISHER_CITY": "book_publisher_city", 
            "COORDINATE_LINKAGE": "coordinate_linkage", 
            "JOURNAL_ABBREV": "journal_abbrev", 
            "PAGE_FIRST": "page_first", 
            "JOURNAL_FULL": "journal_full", 
            "COUNTRY": "country", 
            "ABSTRACT": "abstract", 
            "PDBX_DATABASE_ID_PUBMED": "pdbx_database_id_PubMed", 
            "DETAILS": "details", 
            "TITLE": "title", 
            "RCSB_AUTHORS": "rcsb_authors", 
            "DATABASE_ID_MEDLINE": "database_id_Medline", 
            "PAGE_LAST": "page_last", 
            "ABSTRACT_ID_CAS": "abstract_id_CAS", 
            "DATABASE_ID_CSD": "database_id_CSD", 
            "BOOK_PUBLISHER": "book_publisher", 
            "LANGUAGE": "language", 
            "BOOK_TITLE": "book_title", 
            "PDBX_DATABASE_ID_DOI": "pdbx_database_id_DOI", 
            "JOURNAL_ID_ASTM": "journal_id_ASTM", 
            "ID": "id", 
            "YEAR": "year", 
            "JOURNAL_VOLUME": "journal_volume", 
            "JOURNAL_ID_ISSN": "journal_id_ISSN", 
            "JOURNAL_ISSUE": "journal_issue", 
            "BOOK_ID_ISBN": "book_id_ISBN", 
            "UNPUBLISHED_FLAG": "unpublished_flag"
         }, 
         "ATTRIBUTE_INFO": {
            "JOURNAL_ID_CSD": {
               "APP_TYPE": "char", 
               "ENUMERATION": {}, 
               "FILTER_TYPES": [], 
               "WIDTH": 10, 
               "ORDER": 16, 
               "PRIMARY_KEY": false, 
               "NULLABLE": true, 
               "PRECISION": 0, 
               "IS_CHAR_TYPE": true, 
               "ITERABLE_DELIMITER": null, 
               "CONTENT_CLASSES": []
            }, 
            "BOOK_PUBLISHER_CITY": {
               "APP_TYPE": "char", 
               "ENUMERATION": {}, 
               "FILTER_TYPES": [], 
               "WIDTH": 10, 
               "ORDER": 6, 
               "PRIMARY_KEY": false, 
               "NULLABLE": true, 
               "PRECISION": 0, 
               "IS_CHAR_TYPE": true, 
               "ITERABLE_DELIMITER": null, 
               "CONTENT_CLASSES": []
            }, 
            "JOURNAL_ABBREV": {
               "APP_TYPE": "char", 
               "ENUMERATION": {}, 
               "FILTER_TYPES": [], 
               "WIDTH": 10, 
               "ORDER": 13, 
               "PRIMARY_KEY": false, 
               "NULLABLE": true, 
               "PRECISION": 0, 
               "IS_CHAR_TYPE": true, 
               "ITERABLE_DELIMITER": null, 
               "CONTENT_CLASSES": []
            }, 
            "DATABASE_ID_MEDLINE": {
               "APP_TYPE": "int", 
               "ENUMERATION": {}, 
               "FILTER_TYPES": [], 
               "WIDTH": 10, 
               "ORDER": 11, 
               "PRIMARY_KEY": false, 
               "NULLABLE": true, 
               "PRECISION": 0, 
               "IS_CHAR_TYPE": false, 
               "ITERABLE_DELIMITER": null, 
               "CONTENT_CLASSES": []
            }, 
            "COUNTRY": {
               "APP_TYPE": "char", 
               "ENUMERATION": {}, 
               "FILTER_TYPES": [], 
               "WIDTH": 10, 
               "ORDER": 9, 
               "PRIMARY_KEY": false, 
               "NULLABLE": true, 
               "PRECISION": 0, 
               "IS_CHAR_TYPE": true, 
               "ITERABLE_DELIMITER": null, 
               "CONTENT_CLASSES": []
            }, 
            "ABSTRACT": {
               "APP_TYPE": "char", 
               "ENUMERATION": {}, 
               "FILTER_TYPES": [], 
               "WIDTH": 10, 
               "ORDER": 2, 
               "PRIMARY_KEY": false, 
               "NULLABLE": true, 
               "PRECISION": 0, 
               "IS_CHAR_TYPE": true, 
               "ITERABLE_DELIMITER": null, 
               "CONTENT_CLASSES": []
            }, 
            "PDBX_DATABASE_ID_PUBMED": {
               "APP_TYPE": "int", 
               "ENUMERATION": {}, 
               "FILTER_TYPES": [], 
               "WIDTH": 10, 
               "ORDER": 24, 
               "PRIMARY_KEY": false, 
               "NULLABLE": true, 
               "PRECISION": 0, 
               "IS_CHAR_TYPE": false, 
               "ITERABLE_DELIMITER": null, 
               "CONTENT_CLASSES": []
            }, 
            "TITLE": {
               "APP_TYPE": "char", 
               "ENUMERATION": {}, 
               "FILTER_TYPES": [], 
               "WIDTH": 10, 
               "ORDER": 26, 
               "PRIMARY_KEY": false, 
               "NULLABLE": true, 
               "PRECISION": 0, 
               "IS_CHAR_TYPE": true, 
               "ITERABLE_DELIMITER": null, 
               "CONTENT_CLASSES": []
            }, 
            "JOURNAL_FULL": {
               "APP_TYPE": "char", 
               "ENUMERATION": {}, 
               "FILTER_TYPES": [], 
               "WIDTH": 10, 
               "ORDER": 14, 
               "PRIMARY_KEY": false, 
               "NULLABLE": true, 
               "PRECISION": 0, 
               "IS_CHAR_TYPE": true, 
               "ITERABLE_DELIMITER": null, 
               "CONTENT_CLASSES": []
            }, 
            "PAGE_LAST": {
               "APP_TYPE": "char", 
               "ENUMERATION": {}, 
               "FILTER_TYPES": [], 
               "WIDTH": 10, 
               "ORDER": 22, 
               "PRIMARY_KEY": false, 
               "NULLABLE": true, 
               "PRECISION": 0, 
               "IS_CHAR_TYPE": true, 
               "ITERABLE_DELIMITER": null, 
               "CONTENT_CLASSES": []
            }, 
            "BOOK_PUBLISHER": {
               "APP_TYPE": "char", 
               "ENUMERATION": {}, 
               "FILTER_TYPES": [], 
               "WIDTH": 10, 
               "ORDER": 5, 
               "PRIMARY_KEY": false, 
               "NULLABLE": true, 
               "PRECISION": 0, 
               "IS_CHAR_TYPE": true, 
               "ITERABLE_DELIMITER": null, 
               "CONTENT_CLASSES": []
            }, 
            "LANGUAGE": {
               "APP_TYPE": "char", 
               "ENUMERATION": {}, 
               "FILTER_TYPES": [], 
               "WIDTH": 10, 
               "ORDER": 20, 
               "PRIMARY_KEY": false, 
               "NULLABLE": true, 
               "PRECISION": 0, 
               "IS_CHAR_TYPE": true, 
               "ITERABLE_DELIMITER": null, 
               "CONTENT_CLASSES": []
            }, 
            "PDBX_DATABASE_ID_DOI": {
               "APP_TYPE": "char", 
               "ENUMERATION": {}, 
               "FILTER_TYPES": [], 
               "WIDTH": 10, 
               "ORDER": 23, 
               "PRIMARY_KEY": false, 
               "NULLABLE": true, 
               "PRECISION": 0, 
               "IS_CHAR_TYPE": true, 
               "ITERABLE_DELIMITER": null, 
               "CONTENT_CLASSES": []
            }, 
            "YEAR": {
               "APP_TYPE": "int", 
               "ENUMERATION": {}, 
               "FILTER_TYPES": [], 
               "WIDTH": 10, 
               "ORDER": 28, 
               "PRIMARY_KEY": false, 
               "NULLABLE": true, 
               "PRECISION": 0, 
               "IS_CHAR_TYPE": false, 
               "ITERABLE_DELIMITER": null, 
               "CONTENT_CLASSES": []
            }, 
            "JOURNAL_ISSUE": {
               "APP_TYPE": "char", 
               "ENUMERATION": {}, 
               "FILTER_TYPES": [], 
               "WIDTH": 10, 
               "ORDER": 18, 
               "PRIMARY_KEY": false, 
               "NULLABLE": true, 
               "PRECISION": 0, 
               "IS_CHAR_TYPE": true, 
               "ITERABLE_DELIMITER": null, 
               "CONTENT_CLASSES": []
            }, 
            "BOOK_ID_ISBN": {
               "APP_TYPE": "char", 
               "ENUMERATION": {}, 
               "FILTER_TYPES": [], 
               "WIDTH": 10, 
               "ORDER": 4, 
               "PRIMARY_KEY": false, 
               "NULLABLE": true, 
               "PRECISION": 0, 
               "IS_CHAR_TYPE": true, 
               "ITERABLE_DELIMITER": null, 
               "CONTENT_CLASSES": []
            }, 
            "COORDINATE_LINKAGE": {
               "APP_TYPE": "char", 
               "ENUMERATION": {
                  "n": "n", 
                  "no": "no", 
                  "y": "y", 
                  "yes": "yes"
               }, 
               "FILTER_TYPES": [], 
               "WIDTH": 10, 
               "ORDER": 8, 
               "PRIMARY_KEY": false, 
               "NULLABLE": true, 
               "PRECISION": 0, 
               "IS_CHAR_TYPE": true, 
               "ITERABLE_DELIMITER": null, 
               "CONTENT_CLASSES": []
            }, 
            "BOOK_TITLE": {
               "APP_TYPE": "char", 
               "ENUMERATION": {}, 
               "FILTER_TYPES": [], 
               "WIDTH": 10, 
               "ORDER": 7, 
               "PRIMARY_KEY": false, 
               "NULLABLE": true, 
               "PRECISION": 0, 
               "IS_CHAR_TYPE": true, 
               "ITERABLE_DELIMITER": null, 
               "CONTENT_CLASSES": []
            }, 
            "PAGE_FIRST": {
               "APP_TYPE": "char", 
               "ENUMERATION": {}, 
               "FILTER_TYPES": [], 
               "WIDTH": 10, 
               "ORDER": 21, 
               "PRIMARY_KEY": false, 
               "NULLABLE": true, 
               "PRECISION": 0, 
               "IS_CHAR_TYPE": true, 
               "ITERABLE_DELIMITER": null, 
               "CONTENT_CLASSES": []
            }, 
            "DETAILS": {
               "APP_TYPE": "char", 
               "ENUMERATION": {}, 
               "FILTER_TYPES": [], 
               "WIDTH": 10, 
               "ORDER": 12, 
               "PRIMARY_KEY": false, 
               "NULLABLE": true, 
               "PRECISION": 0, 
               "IS_CHAR_TYPE": true, 
               "ITERABLE_DELIMITER": null, 
               "CONTENT_CLASSES": []
            }, 
            "ABSTRACT_ID_CAS": {
               "APP_TYPE": "char", 
               "ENUMERATION": {}, 
               "FILTER_TYPES": [], 
               "WIDTH": 10, 
               "ORDER": 3, 
               "PRIMARY_KEY": false, 
               "NULLABLE": true, 
               "PRECISION": 0, 
               "IS_CHAR_TYPE": true, 
               "ITERABLE_DELIMITER": null, 
               "CONTENT_CLASSES": []
            }, 
            "ID": {
               "APP_TYPE": "char", 
               "ENUMERATION": {}, 
               "FILTER_TYPES": [], 
               "WIDTH": 10, 
               "ORDER": 1, 
               "PRIMARY_KEY": true, 
               "NULLABLE": false, 
               "PRECISION": 0, 
               "IS_CHAR_TYPE": true, 
               "ITERABLE_DELIMITER": null, 
               "CONTENT_CLASSES": []
            }, 
            "DATABASE_ID_CSD": {
               "APP_TYPE": "char", 
               "ENUMERATION": {}, 
               "FILTER_TYPES": [], 
               "WIDTH": 10, 
               "ORDER": 10, 
               "PRIMARY_KEY": false, 
               "NULLABLE": true, 
               "PRECISION": 0, 
               "IS_CHAR_TYPE": true, 
               "ITERABLE_DELIMITER": null, 
               "CONTENT_CLASSES": []
            }, 
            "RCSB_AUTHORS": {
               "APP_TYPE": "char", 
               "ENUMERATION": {}, 
               "FILTER_TYPES": [], 
               "WIDTH": 10, 
               "ORDER": 25, 
               "PRIMARY_KEY": false, 
               "NULLABLE": true, 
               "PRECISION": 0, 
               "IS_CHAR_TYPE": true, 
               "ITERABLE_DELIMITER": ";", 
               "CONTENT_CLASSES": []
            }, 
            "JOURNAL_VOLUME": {
               "APP_TYPE": "char", 
               "ENUMERATION": {}, 
               "FILTER_TYPES": [], 
               "WIDTH": 10, 
               "ORDER": 19, 
               "PRIMARY_KEY": false, 
               "NULLABLE": true, 
               "PRECISION": 0, 
               "IS_CHAR_TYPE": true, 
               "ITERABLE_DELIMITER": null, 
               "CONTENT_CLASSES": []
            }, 
            "JOURNAL_ID_ISSN": {
               "APP_TYPE": "char", 
               "ENUMERATION": {}, 
               "FILTER_TYPES": [], 
               "WIDTH": 10, 
               "ORDER": 17, 
               "PRIMARY_KEY": false, 
               "NULLABLE": true, 
               "PRECISION": 0, 
               "IS_CHAR_TYPE": true, 
               "ITERABLE_DELIMITER": null, 
               "CONTENT_CLASSES": []
            }, 
            "JOURNAL_ID_ASTM": {
               "APP_TYPE": "char", 
               "ENUMERATION": {}, 
               "FILTER_TYPES": [], 
               "WIDTH": 10, 
               "ORDER": 15, 
               "PRIMARY_KEY": false, 
               "NULLABLE": true, 
               "PRECISION": 0, 
               "IS_CHAR_TYPE": true, 
               "ITERABLE_DELIMITER": null, 
               "CONTENT_CLASSES": []
            }, 
            "UNPUBLISHED_FLAG": {
               "APP_TYPE": "char", 
               "ENUMERATION": {
                  "n": "N", 
                  "y": "Y"
               }, 
               "FILTER_TYPES": [], 
               "WIDTH": 10, 
               "ORDER": 27, 
               "PRIMARY_KEY": false, 
               "NULLABLE": true, 
               "PRECISION": 0, 
               "IS_CHAR_TYPE": true, 
               "ITERABLE_DELIMITER": null, 
               "CONTENT_CLASSES": []
            }
         }
      }
   }, 
   "APP_NAME": "ANY", 
   "SLICE_PARENT_FILTERS": {}, 
   "DATABASE_NAME": "sequence_clusters", 
   "DOCUMENT_DICT": {
      "CONTENT_TYPE_COLLECTION_MAP": {
         "entity_sequence_clusters": [
            "cluster_members_v0_1", 
            "cluster_provenance_v0_1", 
            "entity_members_v0_1"
         ]
      }, 
      "COLLECTION_CONTENT": {
         "cluster_provenance_v0_1": {
            "SLICE_FILTER": null, 
            "EXCLUDE": [], 
            "INCLUDE": [
               "SOFTWARE", 
               "CITATION", 
               "CITATION_AUTHOR"
            ]
         }, 
         "cluster_members_v0_1": {
            "SLICE_FILTER": null, 
            "EXCLUDE": [], 
            "INCLUDE": [
               "RCSB_ENTITY_SEQUENCE_CLUSTER_LIST"
            ]
         }, 
         "entity_members_v0_1": {
            "SLICE_FILTER": null, 
            "EXCLUDE": [], 
            "INCLUDE": [
               "RCSB_ENTITY_SEQUENCE_CLUSTER_LIST"
            ]
         }
      }, 
      "COLLECTION_DOCUMENT_ATTRIBUTE_NAMES": {
         "cluster_provenance_v0_1": [
            "software.name"
         ], 
         "cluster_members_v0_1": [
            "update_id"
         ], 
         "entity_members_v0_1": [
            "update_id"
         ]
      }
   }, 
   "DATABASE_VERSION": "v5", 
   "SELECTION_FILTERS": {}
}